revdb/__init__.py
revdb/db.py
revdb/py.typed
revdb-1.1.4.dist-info/LICENSE
revdb-1.1.4.dist-info/WHEEL
revdb-1.1.4.dist-info/METADATA
revdb-1.1.4.dist-info/RECORD
