Metadata-Version: 2.1
Name: revdb
Version: 1.1.4
Summary: 
Author: Chien
Author-email: a0186163@gmail.com
Requires-Python: >=3.7,<4.0
Classifier: Programming Language :: Python :: 3
Classifier: Programming Language :: Python :: 3.7
Classifier: Programming Language :: Python :: 3.8
Classifier: Programming Language :: Python :: 3.9
Requires-Dist: dnspython (>=2.1.0,<3.0.0)
Requires-Dist: mongoengine (>=0.23.0,<0.24.0)
Requires-Dist: requests (>=2.25.1,<3.0.0)
